.gitignore
CHANGELOG.md
LICENSE
MANIFEST.in
README.rst
setup.py
aloisius/__init__.py
aloisius/exception.py
aloisius/stack.py
aloisius/stack_collection.py
aloisius.egg-info/PKG-INFO
aloisius.egg-info/SOURCES.txt
aloisius.egg-info/dependency_links.txt
aloisius.egg-info/requires.txt
aloisius.egg-info/top_level.txt