Metadata-Version: 1.0
Name: aloisius
Version: 0.4.1
Summary: Create/Update/Delete AWS CloudFormation stacks in parallel
Home-page: https://github.com/adonig/aloisius
Author: Andreas Donig
Author-email: andreas@innwiese.de
License: FreeBSD License
Platform: UNKNOWN
